LICENSE
MANIFEST.in
README.rst
setup.cfg
setup.py
classic_theme/__init__.py
classic_theme/static/admin/css/base.css
classic_theme/static/admin/css/changelists.css
classic_theme/static/admin/css/dashboard.css
classic_theme/static/admin/css/fonts.css
classic_theme/static/admin/css/forms.css
classic_theme/static/admin/css/login.css
classic_theme/static/admin/css/rtl.css
classic_theme/static/admin/css/widgets.css
classic_theme/static/admin/img/changelist-bg.gif
classic_theme/static/admin/img/changelist-bg_rtl.gif
classic_theme/static/admin/img/default-bg-reverse.gif
classic_theme/static/admin/img/default-bg.gif
classic_theme/static/admin/img/deleted-overlay.gif
classic_theme/static/admin/img/icon-no.gif
classic_theme/static/admin/img/icon-unknown.gif
classic_theme/static/admin/img/icon-yes.gif
classic_theme/static/admin/img/icon_addlink.gif
classic_theme/static/admin/img/icon_alert.gif
classic_theme/static/admin/img/icon_calendar.gif
classic_theme/static/admin/img/icon_changelink.gif
classic_theme/static/admin/img/icon_clock.gif
classic_theme/static/admin/img/icon_deletelink.gif
classic_theme/static/admin/img/icon_error.gif
classic_theme/static/admin/img/icon_searchbox.png
classic_theme/static/admin/img/icon_success.gif
classic_theme/static/admin/img/inline-delete.png
classic_theme/static/admin/img/inline-restore-8bit.png
classic_theme/static/admin/img/inline-restore.png
classic_theme/static/admin/img/inline-splitter-bg.gif
classic_theme/static/admin/img/nav-bg-grabber.gif
classic_theme/static/admin/img/nav-bg-reverse.gif
classic_theme/static/admin/img/nav-bg-selected.gif
classic_theme/static/admin/img/nav-bg.gif
classic_theme/static/admin/img/selector-icons.gif
classic_theme/static/admin/img/selector-search.gif
classic_theme/static/admin/img/sorting-icons.gif
classic_theme/static/admin/img/tooltag-add.png
classic_theme/static/admin/img/tooltag-arrowright.png
classic_theme/static/admin/img/gis/move_vertex_off.png
classic_theme/static/admin/img/gis/move_vertex_on.png
django_classic_theme.egg-info/PKG-INFO
django_classic_theme.egg-info/SOURCES.txt
django_classic_theme.egg-info/dependency_links.txt
django_classic_theme.egg-info/top_level.txt